[{"calorie":0.0,"count":0,"distance":0.0,"speed":0.0},{"calorie":0.0,"count":0,"distance":0.0,"speed":0.0},{"calorie":0.0,"count":0,"distance":0.0,"speed":0.0},{"calorie":0.0,"count":0,"distance":0.0,"speed":0.0},{"calorie":0.0,"count":0,"distance":0.0,"speed":0.0},{"calorie":0.0,"count":0,"distance":0.0,"speed":0.0},{"calorie":0.0,"count":0,"distance":0.0,"speed":0.0},{"calorie":0.0,"count":0,"distance":0.0,"speed":0.0},{"calorie":0.0,"count":0,"distance":0.0,"speed":0.0},{"calorie":0.0,"count":0,"distance":0.0,"speed":0.0},{"calorie":0.0,"count":0,"distance":0.0,"speed":0.0},{"calorie":0.0,"count":0,"distance":0.0,"speed":0.0},{"calorie":0.0,"count":0,"distance":0.0,"speed":0.0},{"calorie":0.0,"count":0,"distance":0.0,"speed":0.0},{"calorie":0.0,"count":0,"distance":0.0,"speed":0.0},{"calorie":0.0,"count":0,"distance":0.0,"speed":0.0},{"calorie":0.0,"count":0,"distance":0.0,"speed":0.0},{"calorie":0.0,"count":0,"distance":0.0,"speed":0.0},{"calorie":0.0,"count":0,"distance":0.0,"speed":0.0},{"calorie":0.0,"count":0,"distance":0.0,"speed":0.0},{"calorie":0.0,"count":0,"distance":0.0,"speed":0.0},{"calorie":0.0,"count":0,"distance":0.0,"speed":0.0},{"calorie":0.0,"count":0,"distance":0.0,"speed":0.0},{"calorie":0.0,"count":0,"distance":0.0,"speed":0.0},{"calorie":0.0,"count":0,"distance":0.0,"speed":0.0},{"calorie":0.0,"count":0,"distance":0.0,"speed":0.0},{"calorie":0.0,"count":0,"distance":0.0,"speed":0.0},{"calorie":0.0,"count":0,"distance":0.0,"speed":0.0},{"calorie":0.0,"count":0,"distance":0.0,"speed":0.0},{"calorie":0.0,"count":0,"distance":0.0,"speed":0.0},{"calorie":1.1400000154972076,"count":30,"distance":21.649999618530273,"speed":3.663058280944824},{"calorie":0.28999999165534973,"count":8,"distance":5.800000190734863,"speed":3.700000047683716},{"calorie":1.7700000405311584,"count":48,"distance":36.299999713897705,"speed":4.59204626083374},{"calorie":2.269999921321869,"count":62,"distance":45.65999984741211,"speed":4.200446128845215},{"calorie":0.0,"count":0,"distance":0.0,"speed":0.0},{"calorie":0.0,"count":0,"distance":0.0,"speed":0.0},{"calorie":6.129999876022339,"count":182,"distance":139.4800033569336,"speed":5.420775890350342},{"calorie":2.2400000616908073,"count":62,"distance":47.969998836517334,"speed":5.055150985717773},{"calorie":4.7500001192092896,"count":132,"distance":100.11000156402588,"speed":4.956369400024414},{"calorie":5.089999675750732,"count":137,"distance":103.2700023651123,"speed":4.800164222717285},{"calorie":1.0700000524520874,"count":6,"distance":16.030000686645508,"speed":25.0},{"calorie":0.0,"count":0,"distance":0.0,"speed":0.0},{"calorie":0.0,"count":0,"distance":0.0,"speed":0.0},{"calorie":0.0,"count":0,"distance":0.0,"speed":0.0},{"calorie":2.3599993735551834,"count":62,"distance":47.30999994277954,"speed":5.055817127227783},{"calorie":2.379999816417694,"count":67,"distance":49.92999839782715,"speed":4.62302827835083},{"calorie":11.729998998343945,"count":310,"distance":230.79001021385193,"speed":4.446174621582031},{"calorie":1.4499999433755875,"count":40,"distance":30.009999752044678,"speed":4.575227737426758},{"calorie":0.0,"count":0,"distance":0.0,"speed":0.0},{"calorie":5.989999890327454,"count":181,"distance":138.6400032043457,"speed":5.899999618530273},{"calorie":1.4899999499320984,"count":43,"distance":32.96000099182129,"speed":5.21096134185791},{"calorie":0.8699997663497925,"count":29,"distance":22.860004425048828,"speed":5.821310520172119},{"calorie":0.0,"count":0,"distance":0.0,"speed":0.0},{"calorie":0.0,"count":0,"distance":0.0,"speed":0.0},{"calorie":0.0,"count":0,"distance":0.0,"speed":0.0},{"calorie":0.0,"count":0,"distance":0.0,"speed":0.0},{"calorie":0.0,"count":0,"distance":0.0,"speed":0.0},{"calorie":0.0,"count":0,"distance":0.0,"speed":0.0},{"calorie":0.0,"count":0,"distance":0.0,"speed":0.0},{"calorie":0.0,"count":0,"distance":0.0,"speed":0.0},{"calorie":0.0,"count":0,"distance":0.0,"speed":0.0},{"calorie":0.0,"count":0,"distance":0.0,"speed":0.0},{"calorie":0.0,"count":0,"distance":0.0,"speed":0.0},{"calorie":0.0,"count":0,"distance":0.0,"speed":0.0},{"calorie":0.0,"count":0,"distance":0.0,"speed":0.0},{"calorie":0.0,"count":0,"distance":0.0,"speed":0.0},{"calorie":0.0,"count":0,"distance":0.0,"speed":0.0},{"calorie":0.0,"count":0,"distance":0.0,"speed":0.0},{"calorie":0.0,"count":0,"distance":0.0,"speed":0.0},{"calorie":0.0,"count":0,"distance":0.0,"speed":0.0},{"calorie":0.0,"count":0,"distance":0.0,"speed":0.0},{"calorie":0.0,"count":0,"distance":0.0,"speed":0.0},{"calorie":0.0,"count":0,"distance":0.0,"speed":0.0},{"calorie":0.0,"count":0,"distance":0.0,"speed":0.0},{"calorie":0.0,"count":0,"distance":0.0,"speed":0.0},{"calorie":0.0,"count":0,"distance":0.0,"speed":0.0},{"calorie":0.0,"count":0,"distance":0.0,"speed":0.0},{"calorie":0.0,"count":0,"distance":0.0,"speed":0.0},{"calorie":0.0,"count":0,"distance":0.0,"speed":0.0},{"calorie":0.0,"count":0,"distance":0.0,"speed":0.0},{"calorie":0.0,"count":0,"distance":0.0,"speed":0.0},{"calorie":11.510000064969063,"count":316,"distance":240.1199975013733,"speed":4.9434027671813965},{"calorie":0.0,"count":0,"distance":0.0,"speed":0.0},{"calorie":0.0,"count":0,"distance":0.0,"speed":0.0},{"calorie":0.0,"count":0,"distance":0.0,"speed":0.0},{"calorie":0.0,"count":0,"distance":0.0,"speed":0.0},{"calorie":0.0,"count":0,"distance":0.0,"speed":0.0},{"calorie":0.0,"count":0,"distance":0.0,"speed":0.0},{"calorie":0.0,"count":0,"distance":0.0,"speed":0.0},{"calorie":6.070000052452087,"count":184,"distance":141.5999984741211,"speed":5.259033679962158},{"calorie":0.6299999952316284,"count":17,"distance":12.449999809265137,"speed":4.299999713897705},{"calorie":0.25,"count":7,"distance":5.150000095367432,"speed":4.400000095367432},{"calorie":0.0,"count":0,"distance":0.0,"speed":0.0},{"calorie":0.0,"count":0,"distance":0.0,"speed":0.0},{"calorie":0.0,"count":0,"distance":0.0,"speed":0.0},{"calorie":0.0,"count":0,"distance":0.0,"speed":0.0},{"calorie":0.0,"count":0,"distance":0.0,"speed":0.0},{"calorie":0.0,"count":0,"distance":0.0,"speed":0.0},{"calorie":0.0,"count":0,"distance":0.0,"speed":0.0},{"calorie":0.0,"count":0,"distance":0.0,"speed":0.0},{"calorie":0.0,"count":0,"distance":0.0,"speed":0.0},{"calorie":0.0,"count":0,"distance":0.0,"speed":0.0},{"calorie":0.0,"count":0,"distance":0.0,"speed":0.0},{"calorie":0.0,"count":0,"distance":0.0,"speed":0.0},{"calorie":0.0,"count":0,"distance":0.0,"speed":0.0},{"calorie":4.220000058412552,"count":121,"distance":91.86999845504761,"speed":4.9254350662231445},{"calorie":0.0,"count":0,"distance":0.0,"speed":0.0},{"calorie":7.7300001084804535,"count":242,"distance":187.08999586105347,"speed":5.3979082107543945},{"calorie":9.789998590946198,"count":255,"distance":188.3899974822998,"speed":4.538530349731445},{"calorie":2.479998826980591,"count":64,"distance":44.84002685546875,"speed":3.2000019550323486},{"calorie":20.360000133514404,"count":662,"distance":521.930004119873,"speed":5.909719944000244},{"calorie":4.289999842643738,"count":116,"distance":87.2599983215332,"speed":4.677309989929199},{"calorie":7.809999912977219,"count":251,"distance":196.30000162124634,"speed":5.614559650421143},{"calorie":0.0,"count":0,"distance":0.0,"speed":0.0},{"calorie":1.3899999856948853,"count":38,"distance":28.530000686645508,"speed":4.601957321166992},{"calorie":0.0,"count":0,"distance":0.0,"speed":0.0},{"calorie":0.0,"count":0,"distance":0.0,"speed":0.0},{"calorie":0.0,"count":0,"distance":0.0,"speed":0.0},{"calorie":0.0,"count":0,"distance":0.0,"speed":0.0},{"calorie":0.0,"count":0,"distance":0.0,"speed":0.0},{"calorie":0.0,"count":0,"distance":0.0,"speed":0.0},{"calorie":0.0,"count":0,"distance":0.0,"speed":0.0},{"calorie":0.0,"count":0,"distance":0.0,"speed":0.0},{"calorie":0.0,"count":0,"distance":0.0,"speed":0.0},{"calorie":0.0,"count":0,"distance":0.0,"speed":0.0},{"calorie":4.219999998807907,"count":113,"distance":83.38999843597412,"speed":4.526564121246338},{"calorie":2.0100000202655792,"count":54,"distance":40.22999954223633,"speed":4.3469462394714355},{"calorie":0.0,"count":0,"distance":0.0,"speed":0.0},{"calorie":0.0,"count":0,"distance":0.0,"speed":0.0},{"calorie":0.0,"count":0,"distance":0.0,"speed":0.0},{"calorie":0.0,"count":0,"distance":0.0,"speed":0.0},{"calorie":0.0,"count":0,"distance":0.0,"speed":0.0},{"calorie":0.0,"count":0,"distance":0.0,"speed":0.0},{"calorie":0.0,"count":0,"distance":0.0,"speed":0.0},{"calorie":0.0,"count":0,"distance":0.0,"speed":0.0},{"calorie":0.0,"count":0,"distance":0.0,"speed":0.0},{"calorie":0.0,"count":0,"distance":0.0,"speed":0.0},{"calorie":0.0,"count":0,"distance":0.0,"speed":0.0},{"calorie":0.0,"count":0,"distance":0.0,"speed":0.0},{"calorie":0.0,"count":0,"distance":0.0,"speed":0.0},{"calorie":0.0,"count":0,"distance":0.0,"speed":0.0},{"calorie":0.0,"count":0,"distance":0.0,"speed":0.0},{"calorie":0.0,"count":0,"distance":0.0,"speed":0.0},{"calorie":0.0,"count":0,"distance":0.0,"speed":0.0}]