[{"mCalorie":5.519999742507935,"mDistance":98.37000274658203,"mNowHealthyStep":0,"mRunStepCount":0,"mSpeed":3.9695019721984863,"mStartTime":0,"mStepCount":135,"mTimeUnit":600000,"mTotalActiveTime":89213.20936615815,"mWalkStepCount":135},{"mCalorie":0.0,"mDistance":0.0,"mNowHealthyStep":0,"mRunStepCount":0,"mSpeed":0.0,"mStartTime":0,"mStepCount":0,"mTimeUnit":600000,"mTotalActiveTime":0.0,"mWalkStepCount":0},{"mCalorie":0.0,"mDistance":0.0,"mNowHealthyStep":0,"mRunStepCount":0,"mSpeed":0.0,"mStartTime":0,"mStepCount":0,"mTimeUnit":600000,"mTotalActiveTime":0.0,"mWalkStepCount":0},{"mCalorie":0.0,"mDistance":0.0,"mNowHealthyStep":0,"mRunStepCount":0,"mSpeed":0.0,"mStartTime":0,"mStepCount":0,"mTimeUnit":600000,"mTotalActiveTime":0.0,"mWalkStepCount":0},{"mCalorie":0.0,"mDistance":0.0,"mNowHealthyStep":0,"mRunStepCount":0,"mSpeed":0.0,"mStartTime":0,"mStepCount":0,"mTimeUnit":600000,"mTotalActiveTime":0.0,"mWalkStepCount":0},{"mCalorie":0.0,"mDistance":0.0,"mNowHealthyStep":0,"mRunStepCount":0,"mSpeed":0.0,"mStartTime":0,"mStepCount":0,"mTimeUnit":600000,"mTotalActiveTime":0.0,"mWalkStepCount":0},{"mCalorie":0.0,"mDistance":0.0,"mNowHealthyStep":0,"mRunStepCount":0,"mSpeed":0.0,"mStartTime":0,"mStepCount":0,"mTimeUnit":600000,"mTotalActiveTime":0.0,"mWalkStepCount":0},{"mCalorie":1.7499999850988388,"mDistance":31.860000371932983,"mNowHealthyStep":0,"mRunStepCount":0,"mSpeed":4.628452301025391,"mStartTime":0,"mStepCount":42,"mTimeUnit":600000,"mTotalActiveTime":24780.636943318706,"mWalkStepCount":42},{"mCalorie":0.6700000166893005,"mDistance":11.75,"mNowHealthyStep":0,"mRunStepCount":0,"mSpeed":4.400000095367432,"mStartTime":0,"mStepCount":16,"mTimeUnit":600000,"mTotalActiveTime":9613.636155266411,"mWalkStepCount":16},{"mCalorie":0.0,"mDistance":0.0,"mNowHealthyStep":0,"mRunStepCount":0,"mSpeed":0.0,"mStartTime":0,"mStepCount":0,"mTimeUnit":600000,"mTotalActiveTime":0.0,"mWalkStepCount":0},{"mCalorie":0.0,"mDistance":0.0,"mNowHealthyStep":0,"mRunStepCount":0,"mSpeed":0.0,"mStartTime":0,"mStepCount":0,"mTimeUnit":600000,"mTotalActiveTime":0.0,"mWalkStepCount":0},{"mCalorie":0.0,"mDistance":0.0,"mNowHealthyStep":0,"mRunStepCount":0,"mSpeed":0.0,"mStartTime":0,"mStepCount":0,"mTimeUnit":600000,"mTotalActiveTime":0.0,"mWalkStepCount":0},{"mCalorie":1.1399999856948853,"mDistance":19.479999542236328,"mNowHealthyStep":0,"mRunStepCount":0,"mSpeed":4.099999904632568,"mStartTime":0,"mStepCount":27,"mTimeUnit":600000,"mTotalActiveTime":17104.390239817698,"mWalkStepCount":27},{"mCalorie":0.0,"mDistance":0.0,"mNowHealthyStep":0,"mRunStepCount":0,"mSpeed":0.0,"mStartTime":0,"mStepCount":0,"mTimeUnit":600000,"mTotalActiveTime":0.0,"mWalkStepCount":0},{"mCalorie":0.0,"mDistance":0.0,"mNowHealthyStep":0,"mRunStepCount":0,"mSpeed":0.0,"mStartTime":0,"mStepCount":0,"mTimeUnit":600000,"mTotalActiveTime":0.0,"mWalkStepCount":0},{"mCalorie":0.0,"mDistance":0.0,"mNowHealthyStep":0,"mRunStepCount":0,"mSpeed":0.0,"mStartTime":0,"mStepCount":0,"mTimeUnit":600000,"mTotalActiveTime":0.0,"mWalkStepCount":0},{"mCalorie":0.0,"mDistance":0.0,"mNowHealthyStep":0,"mRunStepCount":0,"mSpeed":0.0,"mStartTime":0,"mStepCount":0,"mTimeUnit":600000,"mTotalActiveTime":0.0,"mWalkStepCount":0},{"mCalorie":0.0,"mDistance":0.0,"mNowHealthyStep":0,"mRunStepCount":0,"mSpeed":0.0,"mStartTime":0,"mStepCount":0,"mTimeUnit":600000,"mTotalActiveTime":0.0,"mWalkStepCount":0},{"mCalorie":1.1399998664855957,"mDistance":20.03000259399414,"mNowHealthyStep":0,"mRunStepCount":0,"mSpeed":4.266721248626709,"mStartTime":0,"mStepCount":27,"mTimeUnit":600000,"mTotalActiveTime":16900.09849169023,"mWalkStepCount":27},{"mCalorie":0.7200000658631325,"mDistance":12.370000064373016,"mNowHealthyStep":0,"mRunStepCount":0,"mSpeed":3.814587116241455,"mStartTime":0,"mStepCount":17,"mTimeUnit":600000,"mTotalActiveTime":11674.133933427389,"mWalkStepCount":17},{"mCalorie":0.0,"mDistance":0.0,"mNowHealthyStep":0,"mRunStepCount":0,"mSpeed":0.0,"mStartTime":0,"mStepCount":0,"mTimeUnit":600000,"mTotalActiveTime":0.0,"mWalkStepCount":0},{"mCalorie":0.0,"mDistance":0.0,"mNowHealthyStep":0,"mRunStepCount":0,"mSpeed":0.0,"mStartTime":0,"mStepCount":0,"mTimeUnit":600000,"mTotalActiveTime":0.0,"mWalkStepCount":0},{"mCalorie":0.0,"mDistance":0.0,"mNowHealthyStep":0,"mRunStepCount":0,"mSpeed":0.0,"mStartTime":0,"mStepCount":0,"mTimeUnit":600000,"mTotalActiveTime":0.0,"mWalkStepCount":0},{"mCalorie":0.0,"mDistance":0.0,"mNowHealthyStep":0,"mRunStepCount":0,"mSpeed":0.0,"mStartTime":0,"mStepCount":0,"mTimeUnit":600000,"mTotalActiveTime":0.0,"mWalkStepCount":0},{"mCalorie":0.0,"mDistance":0.0,"mNowHealthyStep":0,"mRunStepCount":0,"mSpeed":0.0,"mStartTime":0,"mStepCount":0,"mTimeUnit":600000,"mTotalActiveTime":0.0,"mWalkStepCount":0},{"mCalorie":0.0,"mDistance":0.0,"mNowHealthyStep":0,"mRunStepCount":0,"mSpeed":0.0,"mStartTime":0,"mStepCount":0,"mTimeUnit":600000,"mTotalActiveTime":0.0,"mWalkStepCount":0},{"mCalorie":0.0,"mDistance":0.0,"mNowHealthyStep":0,"mRunStepCount":0,"mSpeed":0.0,"mStartTime":0,"mStepCount":0,"mTimeUnit":600000,"mTotalActiveTime":0.0,"mWalkStepCount":0},{"mCalorie":0.0,"mDistance":0.0,"mNowHealthyStep":0,"mRunStepCount":0,"mSpeed":0.0,"mStartTime":0,"mStepCount":0,"mTimeUnit":600000,"mTotalActiveTime":0.0,"mWalkStepCount":0},{"mCalorie":0.0,"mDistance":0.0,"mNowHealthyStep":0,"mRunStepCount":0,"mSpeed":0.0,"mStartTime":0,"mStepCount":0,"mTimeUnit":600000,"mTotalActiveTime":0.0,"mWalkStepCount":0},{"mCalorie":0.0,"mDistance":0.0,"mNowHealthyStep":0,"mRunStepCount":0,"mSpeed":0.0,"mStartTime":0,"mStepCount":0,"mTimeUnit":600000,"mTotalActiveTime":0.0,"mWalkStepCount":0},{"mCalorie":0.0,"mDistance":0.0,"mNowHealthyStep":0,"mRunStepCount":0,"mSpeed":0.0,"mStartTime":0,"mStepCount":0,"mTimeUnit":600000,"mTotalActiveTime":0.0,"mWalkStepCount":0},{"mCalorie":0.0,"mDistance":0.0,"mNowHealthyStep":0,"mRunStepCount":0,"mSpeed":0.0,"mStartTime":0,"mStepCount":0,"mTimeUnit":600000,"mTotalActiveTime":0.0,"mWalkStepCount":0},{"mCalorie":0.0,"mDistance":0.0,"mNowHealthyStep":0,"mRunStepCount":0,"mSpeed":0.0,"mStartTime":0,"mStepCount":0,"mTimeUnit":600000,"mTotalActiveTime":0.0,"mWalkStepCount":0},{"mCalorie":0.0,"mDistance":0.0,"mNowHealthyStep":0,"mRunStepCount":0,"mSpeed":0.0,"mStartTime":0,"mStepCount":0,"mTimeUnit":600000,"mTotalActiveTime":0.0,"mWalkStepCount":0},{"mCalorie":0.0,"mDistance":0.0,"mNowHealthyStep":0,"mRunStepCount":0,"mSpeed":0.0,"mStartTime":0,"mStepCount":0,"mTimeUnit":600000,"mTotalActiveTime":0.0,"mWalkStepCount":0},{"mCalorie":0.0,"mDistance":0.0,"mNowHealthyStep":0,"mRunStepCount":0,"mSpeed":0.0,"mStartTime":0,"mStepCount":0,"mTimeUnit":600000,"mTotalActiveTime":0.0,"mWalkStepCount":0},{"mCalorie":0.0,"mDistance":0.0,"mNowHealthyStep":0,"mRunStepCount":0,"mSpeed":0.0,"mStartTime":0,"mStepCount":0,"mTimeUnit":600000,"mTotalActiveTime":0.0,"mWalkStepCount":0},{"mCalorie":0.0,"mDistance":0.0,"mNowHealthyStep":0,"mRunStepCount":0,"mSpeed":0.0,"mStartTime":0,"mStepCount":0,"mTimeUnit":600000,"mTotalActiveTime":0.0,"mWalkStepCount":0},{"mCalorie":0.0,"mDistance":0.0,"mNowHealthyStep":0,"mRunStepCount":0,"mSpeed":0.0,"mStartTime":0,"mStepCount":0,"mTimeUnit":600000,"mTotalActiveTime":0.0,"mWalkStepCount":0},{"mCalorie":0.0,"mDistance":0.0,"mNowHealthyStep":0,"mRunStepCount":0,"mSpeed":0.0,"mStartTime":0,"mStepCount":0,"mTimeUnit":600000,"mTotalActiveTime":0.0,"mWalkStepCount":0},{"mCalorie":0.0,"mDistance":0.0,"mNowHealthyStep":0,"mRunStepCount":0,"mSpeed":0.0,"mStartTime":0,"mStepCount":0,"mTimeUnit":600000,"mTotalActiveTime":0.0,"mWalkStepCount":0},{"mCalorie":0.0,"mDistance":0.0,"mNowHealthyStep":0,"mRunStepCount":0,"mSpeed":0.0,"mStartTime":0,"mStepCount":0,"mTimeUnit":600000,"mTotalActiveTime":0.0,"mWalkStepCount":0},{"mCalorie":0.0,"mDistance":0.0,"mNowHealthyStep":0,"mRunStepCount":0,"mSpeed":0.0,"mStartTime":0,"mStepCount":0,"mTimeUnit":600000,"mTotalActiveTime":0.0,"mWalkStepCount":0},{"mCalorie":0.0,"mDistance":0.0,"mNowHealthyStep":0,"mRunStepCount":0,"mSpeed":0.0,"mStartTime":0,"mStepCount":0,"mTimeUnit":600000,"mTotalActiveTime":0.0,"mWalkStepCount":0},{"mCalorie":0.0,"mDistance":0.0,"mNowHealthyStep":0,"mRunStepCount":0,"mSpeed":0.0,"mStartTime":0,"mStepCount":0,"mTimeUnit":600000,"mTotalActiveTime":0.0,"mWalkStepCount":0},{"mCalorie":0.0,"mDistance":0.0,"mNowHealthyStep":0,"mRunStepCount":0,"mSpeed":0.0,"mStartTime":0,"mStepCount":0,"mTimeUnit":600000,"mTotalActiveTime":0.0,"mWalkStepCount":0},{"mCalorie":0.0,"mDistance":0.0,"mNowHealthyStep":0,"mRunStepCount":0,"mSpeed":0.0,"mStartTime":0,"mStepCount":0,"mTimeUnit":600000,"mTotalActiveTime":0.0,"mWalkStepCount":0},{"mCalorie":0.0,"mDistance":0.0,"mNowHealthyStep":0,"mRunStepCount":0,"mSpeed":0.0,"mStartTime":0,"mStepCount":0,"mTimeUnit":600000,"mTotalActiveTime":0.0,"mWalkStepCount":0},{"mCalorie":0.0,"mDistance":0.0,"mNowHealthyStep":0,"mRunStepCount":0,"mSpeed":0.0,"mStartTime":0,"mStepCount":0,"mTimeUnit":600000,"mTotalActiveTime":0.0,"mWalkStepCount":0},{"mCalorie":0.0,"mDistance":0.0,"mNowHealthyStep":0,"mRunStepCount":0,"mSpeed":0.0,"mStartTime":0,"mStepCount":0,"mTimeUnit":600000,"mTotalActiveTime":0.0,"mWalkStepCount":0},{"mCalorie":0.0,"mDistance":0.0,"mNowHealthyStep":0,"mRunStepCount":0,"mSpeed":0.0,"mStartTime":0,"mStepCount":0,"mTimeUnit":600000,"mTotalActiveTime":0.0,"mWalkStepCount":0},{"mCalorie":0.0,"mDistance":0.0,"mNowHealthyStep":0,"mRunStepCount":0,"mSpeed":0.0,"mStartTime":0,"mStepCount":0,"mTimeUnit":600000,"mTotalActiveTime":0.0,"mWalkStepCount":0},{"mCalorie":0.0,"mDistance":0.0,"mNowHealthyStep":0,"mRunStepCount":0,"mSpeed":0.0,"mStartTime":0,"mStepCount":0,"mTimeUnit":600000,"mTotalActiveTime":0.0,"mWalkStepCount":0},{"mCalorie":0.0,"mDistance":0.0,"mNowHealthyStep":0,"mRunStepCount":0,"mSpeed":0.0,"mStartTime":0,"mStepCount":0,"mTimeUnit":600000,"mTotalActiveTime":0.0,"mWalkStepCount":0},{"mCalorie":0.0,"mDistance":0.0,"mNowHealthyStep":0,"mRunStepCount":0,"mSpeed":0.0,"mStartTime":0,"mStepCount":0,"mTimeUnit":600000,"mTotalActiveTime":0.0,"mWalkStepCount":0},{"mCalorie":0.0,"mDistance":0.0,"mNowHealthyStep":0,"mRunStepCount":0,"mSpeed":0.0,"mStartTime":0,"mStepCount":0,"mTimeUnit":600000,"mTotalActiveTime":0.0,"mWalkStepCount":0},{"mCalorie":0.9100000262260437,"mDistance":15.079998016357422,"mNowHealthyStep":0,"mRunStepCount":0,"mSpeed":3.7647993564605713,"mStartTime":0,"mStepCount":21,"mTimeUnit":600000,"mTotalActiveTime":14419.89007082834,"mWalkStepCount":21},{"mCalorie":0.0,"mDistance":0.0,"mNowHealthyStep":0,"mRunStepCount":0,"mSpeed":0.0,"mStartTime":0,"mStepCount":0,"mTimeUnit":600000,"mTotalActiveTime":0.0,"mWalkStepCount":0},{"mCalorie":0.25999999046325684,"mDistance":4.360000133514404,"mNowHealthyStep":0,"mRunStepCount":0,"mSpeed":4.400000095367432,"mStartTime":0,"mStepCount":6,"mTimeUnit":600000,"mTotalActiveTime":3567.2727591932303,"mWalkStepCount":6},{"mCalorie":3.019999921321869,"mDistance":44.18000030517578,"mNowHealthyStep":0,"mRunStepCount":0,"mSpeed":4.228485107421875,"mStartTime":0,"mStepCount":62,"mTimeUnit":600000,"mTotalActiveTime":37613.47164223791,"mWalkStepCount":62},{"mCalorie":0.0,"mDistance":0.0,"mNowHealthyStep":0,"mRunStepCount":0,"mSpeed":0.0,"mStartTime":0,"mStepCount":0,"mTimeUnit":600000,"mTotalActiveTime":0.0,"mWalkStepCount":0},{"mCalorie":0.0,"mDistance":0.0,"mNowHealthyStep":0,"mRunStepCount":0,"mSpeed":0.0,"mStartTime":0,"mStepCount":0,"mTimeUnit":600000,"mTotalActiveTime":0.0,"mWalkStepCount":0},{"mCalorie":0.0,"mDistance":0.0,"mNowHealthyStep":0,"mRunStepCount":0,"mSpeed":0.0,"mStartTime":0,"mStepCount":0,"mTimeUnit":600000,"mTotalActiveTime":0.0,"mWalkStepCount":0},{"mCalorie":3.5200001299381256,"mDistance":63.73000240325928,"mNowHealthyStep":0,"mRunStepCount":0,"mSpeed":4.729619026184082,"mStartTime":0,"mStepCount":85,"mTimeUnit":600000,"mTotalActiveTime":48508.77011643433,"mWalkStepCount":85},{"mCalorie":1.6800000071525574,"mDistance":31.59999942779541,"mNowHealthyStep":0,"mRunStepCount":0,"mSpeed":5.114742279052734,"mStartTime":0,"mStepCount":41,"mTimeUnit":600000,"mTotalActiveTime":22241.589483020827,"mWalkStepCount":41},{"mCalorie":2.5999999046325684,"mDistance":48.41999816894531,"mNowHealthyStep":0,"mRunStepCount":0,"mSpeed":4.900000095367432,"mStartTime":0,"mStepCount":64,"mTimeUnit":600000,"mTotalActiveTime":35573.87551339061,"mWalkStepCount":64},{"mCalorie":2.689999997615814,"mDistance":49.75000190734863,"mNowHealthyStep":0,"mRunStepCount":0,"mSpeed":4.752935409545898,"mStartTime":0,"mStepCount":66,"mTimeUnit":600000,"mTotalActiveTime":37681.976835009846,"mWalkStepCount":66},{"mCalorie":0.0,"mDistance":0.0,"mNowHealthyStep":0,"mRunStepCount":0,"mSpeed":0.0,"mStartTime":0,"mStepCount":0,"mTimeUnit":600000,"mTotalActiveTime":0.0,"mWalkStepCount":0},{"mCalorie":5.829998672008514,"mDistance":95.93999481201172,"mNowHealthyStep":0,"mRunStepCount":0,"mSpeed":4.759049892425537,"mStartTime":0,"mStepCount":130,"mTimeUnit":600000,"mTotalActiveTime":72574.14395879424,"mWalkStepCount":130},{"mCalorie":5.450000107288361,"mDistance":94.1399998664856,"mNowHealthyStep":0,"mRunStepCount":0,"mSpeed":5.1591410636901855,"mStartTime":0,"mStepCount":135,"mTimeUnit":600000,"mTotalActiveTime":65690.00148288615,"mWalkStepCount":135},{"mCalorie":0.0,"mDistance":0.0,"mNowHealthyStep":0,"mRunStepCount":0,"mSpeed":0.0,"mStartTime":0,"mStepCount":0,"mTimeUnit":600000,"mTotalActiveTime":0.0,"mWalkStepCount":0},{"mCalorie":0.64000004529953,"mDistance":11.430000305175781,"mNowHealthyStep":0,"mRunStepCount":0,"mSpeed":6.292896747589111,"mStartTime":0,"mStepCount":13,"mTimeUnit":600000,"mTotalActiveTime":6538.801246722685,"mWalkStepCount":13},{"mCalorie":13.53000020980835,"mDistance":239.55999946594238,"mNowHealthyStep":0,"mRunStepCount":3,"mSpeed":4.716312885284424,"mStartTime":0,"mStepCount":316,"mTimeUnit":600000,"mTotalActiveTime":182858.09057293873,"mWalkStepCount":313},{"mCalorie":6.090000152587891,"mDistance":109.57999801635742,"mNowHealthyStep":0,"mRunStepCount":0,"mSpeed":4.504968643188477,"mStartTime":0,"mStepCount":147,"mTimeUnit":600000,"mTotalActiveTime":87567.30957000065,"mWalkStepCount":147},{"mCalorie":2.700000077486038,"mDistance":49.859999656677246,"mNowHealthyStep":0,"mRunStepCount":0,"mSpeed":4.746133804321289,"mStartTime":0,"mStepCount":66,"mTimeUnit":600000,"mTotalActiveTime":37819.414674423424,"mWalkStepCount":66},{"mCalorie":0.0,"mDistance":0.0,"mNowHealthyStep":0,"mRunStepCount":0,"mSpeed":0.0,"mStartTime":0,"mStepCount":0,"mTimeUnit":600000,"mTotalActiveTime":0.0,"mWalkStepCount":0},{"mCalorie":1.9200001955032349,"mDistance":34.89000129699707,"mNowHealthyStep":0,"mRunStepCount":0,"mSpeed":4.438708782196045,"mStartTime":0,"mStepCount":47,"mTimeUnit":600000,"mTotalActiveTime":28297.41951024098,"mWalkStepCount":47},{"mCalorie":0.0,"mDistance":0.0,"mNowHealthyStep":0,"mRunStepCount":0,"mSpeed":0.0,"mStartTime":0,"mStepCount":0,"mTimeUnit":600000,"mTotalActiveTime":0.0,"mWalkStepCount":0},{"mCalorie":0.0,"mDistance":0.0,"mNowHealthyStep":0,"mRunStepCount":0,"mSpeed":0.0,"mStartTime":0,"mStepCount":0,"mTimeUnit":600000,"mTotalActiveTime":0.0,"mWalkStepCount":0},{"mCalorie":0.0,"mDistance":0.0,"mNowHealthyStep":0,"mRunStepCount":0,"mSpeed":0.0,"mStartTime":0,"mStepCount":0,"mTimeUnit":600000,"mTotalActiveTime":0.0,"mWalkStepCount":0},{"mCalorie":0.0,"mDistance":0.0,"mNowHealthyStep":0,"mRunStepCount":0,"mSpeed":0.0,"mStartTime":0,"mStepCount":0,"mTimeUnit":600000,"mTotalActiveTime":0.0,"mWalkStepCount":0},{"mCalorie":0.7000000476837158,"mDistance":12.920000076293945,"mNowHealthyStep":0,"mRunStepCount":0,"mSpeed":4.973328113555908,"mStartTime":0,"mStepCount":17,"mTimeUnit":600000,"mTotalActiveTime":9352.288691325119,"mWalkStepCount":17},{"mCalorie":3.0799999237060547,"mDistance":53.220001220703125,"mNowHealthyStep":0,"mRunStepCount":0,"mSpeed":4.033867835998535,"mStartTime":0,"mStepCount":73,"mTimeUnit":600000,"mTotalActiveTime":47495.85513803095,"mWalkStepCount":73},{"mCalorie":4.219999074935913,"mDistance":78.13000297546387,"mNowHealthyStep":0,"mRunStepCount":0,"mSpeed":4.90378999710083,"mStartTime":0,"mStepCount":104,"mTimeUnit":600000,"mTotalActiveTime":57357.273109368936,"mWalkStepCount":104},{"mCalorie":2.630000114440918,"mDistance":49.459999084472656,"mNowHealthyStep":0,"mRunStepCount":0,"mSpeed":5.099999904632568,"mStartTime":0,"mStepCount":65,"mTimeUnit":600000,"mTotalActiveTime":34912.94118307041,"mWalkStepCount":65},{"mCalorie":3.909999370574951,"mDistance":73.22999382019043,"mNowHealthyStep":0,"mRunStepCount":0,"mSpeed":5.122447967529297,"mStartTime":0,"mStepCount":96,"mTimeUnit":600000,"mTotalActiveTime":51465.23163703387,"mWalkStepCount":96},{"mCalorie":0.0,"mDistance":0.0,"mNowHealthyStep":0,"mRunStepCount":0,"mSpeed":0.0,"mStartTime":0,"mStepCount":0,"mTimeUnit":600000,"mTotalActiveTime":0.0,"mWalkStepCount":0},{"mCalorie":0.0,"mDistance":0.0,"mNowHealthyStep":0,"mRunStepCount":0,"mSpeed":0.0,"mStartTime":0,"mStepCount":0,"mTimeUnit":600000,"mTotalActiveTime":0.0,"mWalkStepCount":0},{"mCalorie":0.0,"mDistance":0.0,"mNowHealthyStep":0,"mRunStepCount":0,"mSpeed":0.0,"mStartTime":0,"mStepCount":0,"mTimeUnit":600000,"mTotalActiveTime":0.0,"mWalkStepCount":0},{"mCalorie":0.929999977350235,"mDistance":15.620000123977661,"mNowHealthyStep":0,"mRunStepCount":0,"mSpeed":4.03158712387085,"mStartTime":0,"mStepCount":22,"mTimeUnit":600000,"mTotalActiveTime":13947.85735733655,"mWalkStepCount":22},{"mCalorie":0.0,"mDistance":0.0,"mNowHealthyStep":0,"mRunStepCount":0,"mSpeed":0.0,"mStartTime":0,"mStepCount":0,"mTimeUnit":600000,"mTotalActiveTime":0.0,"mWalkStepCount":0},{"mCalorie":0.0,"mDistance":0.0,"mNowHealthyStep":0,"mRunStepCount":0,"mSpeed":0.0,"mStartTime":0,"mStepCount":0,"mTimeUnit":600000,"mTotalActiveTime":0.0,"mWalkStepCount":0},{"mCalorie":0.6399999856948853,"mDistance":11.239999771118164,"mNowHealthyStep":0,"mRunStepCount":0,"mSpeed":4.999999523162842,"mStartTime":0,"mStepCount":15,"mTimeUnit":600000,"mTotalActiveTime":8092.800606994686,"mWalkStepCount":15},{"mCalorie":0.0,"mDistance":0.0,"mNowHealthyStep":0,"mRunStepCount":0,"mSpeed":0.0,"mStartTime":0,"mStepCount":0,"mTimeUnit":600000,"mTotalActiveTime":0.0,"mWalkStepCount":0},{"mCalorie":0.0,"mDistance":0.0,"mNowHealthyStep":0,"mRunStepCount":0,"mSpeed":0.0,"mStartTime":0,"mStepCount":0,"mTimeUnit":600000,"mTotalActiveTime":0.0,"mWalkStepCount":0},{"mCalorie":0.0,"mDistance":0.0,"mNowHealthyStep":0,"mRunStepCount":0,"mSpeed":0.0,"mStartTime":0,"mStepCount":0,"mTimeUnit":600000,"mTotalActiveTime":0.0,"mWalkStepCount":0},{"mCalorie":0.0,"mDistance":0.0,"mNowHealthyStep":0,"mRunStepCount":0,"mSpeed":0.0,"mStartTime":0,"mStepCount":0,"mTimeUnit":600000,"mTotalActiveTime":0.0,"mWalkStepCount":0},{"mCalorie":0.0,"mDistance":0.0,"mNowHealthyStep":0,"mRunStepCount":0,"mSpeed":0.0,"mStartTime":0,"mStepCount":0,"mTimeUnit":600000,"mTotalActiveTime":0.0,"mWalkStepCount":0},{"mCalorie":0.0,"mDistance":0.0,"mNowHealthyStep":0,"mRunStepCount":0,"mSpeed":0.0,"mStartTime":0,"mStepCount":0,"mTimeUnit":600000,"mTotalActiveTime":0.0,"mWalkStepCount":0},{"mCalorie":0.0,"mDistance":0.0,"mNowHealthyStep":0,"mRunStepCount":0,"mSpeed":0.0,"mStartTime":0,"mStepCount":0,"mTimeUnit":600000,"mTotalActiveTime":0.0,"mWalkStepCount":0},{"mCalorie":0.0,"mDistance":0.0,"mNowHealthyStep":0,"mRunStepCount":0,"mSpeed":0.0,"mStartTime":0,"mStepCount":0,"mTimeUnit":600000,"mTotalActiveTime":0.0,"mWalkStepCount":0},{"mCalorie":0.0,"mDistance":0.0,"mNowHealthyStep":0,"mRunStepCount":0,"mSpeed":0.0,"mStartTime":0,"mStepCount":0,"mTimeUnit":600000,"mTotalActiveTime":0.0,"mWalkStepCount":0},{"mCalorie":0.0,"mDistance":0.0,"mNowHealthyStep":0,"mRunStepCount":0,"mSpeed":0.0,"mStartTime":0,"mStepCount":0,"mTimeUnit":600000,"mTotalActiveTime":0.0,"mWalkStepCount":0},{"mCalorie":0.0,"mDistance":0.0,"mNowHealthyStep":0,"mRunStepCount":0,"mSpeed":0.0,"mStartTime":0,"mStepCount":0,"mTimeUnit":600000,"mTotalActiveTime":0.0,"mWalkStepCount":0},{"mCalorie":0.0,"mDistance":0.0,"mNowHealthyStep":0,"mRunStepCount":0,"mSpeed":0.0,"mStartTime":0,"mStepCount":0,"mTimeUnit":600000,"mTotalActiveTime":0.0,"mWalkStepCount":0},{"mCalorie":3.0500000715255737,"mDistance":38.79999923706055,"mNowHealthyStep":0,"mRunStepCount":0,"mSpeed":4.448974609375,"mStartTime":0,"mStepCount":56,"mTimeUnit":600000,"mTotalActiveTime":31395.999041037132,"mWalkStepCount":56},{"mCalorie":6.509999871253967,"mDistance":117.64999961853027,"mNowHealthyStep":0,"mRunStepCount":0,"mSpeed":5.108323097229004,"mStartTime":0,"mStepCount":158,"mTimeUnit":600000,"mTotalActiveTime":82911.75127553382,"mWalkStepCount":158},{"mCalorie":0.0,"mDistance":0.0,"mNowHealthyStep":0,"mRunStepCount":0,"mSpeed":0.0,"mStartTime":0,"mStepCount":0,"mTimeUnit":600000,"mTotalActiveTime":0.0,"mWalkStepCount":0},{"mCalorie":0.0,"mDistance":0.0,"mNowHealthyStep":0,"mRunStepCount":0,"mSpeed":0.0,"mStartTime":0,"mStepCount":0,"mTimeUnit":600000,"mTotalActiveTime":0.0,"mWalkStepCount":0},{"mCalorie":2.7700000405311584,"mDistance":49.34000015258789,"mNowHealthyStep":0,"mRunStepCount":0,"mSpeed":4.5447821617126465,"mStartTime":0,"mStepCount":66,"mTimeUnit":600000,"mTotalActiveTime":39083.0612639438,"mWalkStepCount":66},{"mCalorie":0.0,"mDistance":0.0,"mNowHealthyStep":0,"mRunStepCount":0,"mSpeed":0.0,"mStartTime":0,"mStepCount":0,"mTimeUnit":600000,"mTotalActiveTime":0.0,"mWalkStepCount":0},{"mCalorie":0.0,"mDistance":0.0,"mNowHealthyStep":0,"mRunStepCount":0,"mSpeed":0.0,"mStartTime":0,"mStepCount":0,"mTimeUnit":600000,"mTotalActiveTime":0.0,"mWalkStepCount":0},{"mCalorie":0.0,"mDistance":0.0,"mNowHealthyStep":0,"mRunStepCount":0,"mSpeed":0.0,"mStartTime":0,"mStepCount":0,"mTimeUnit":600000,"mTotalActiveTime":0.0,"mWalkStepCount":0},{"mCalorie":3.8000000715255737,"mDistance":72.47999954223633,"mNowHealthyStep":0,"mRunStepCount":0,"mSpeed":5.384167671203613,"mStartTime":0,"mStepCount":93,"mTimeUnit":600000,"mTotalActiveTime":48462.085695469425,"mWalkStepCount":93},{"mCalorie":0.0,"mDistance":0.0,"mNowHealthyStep":0,"mRunStepCount":0,"mSpeed":0.0,"mStartTime":0,"mStepCount":0,"mTimeUnit":600000,"mTotalActiveTime":0.0,"mWalkStepCount":0},{"mCalorie":0.0,"mDistance":0.0,"mNowHealthyStep":0,"mRunStepCount":0,"mSpeed":0.0,"mStartTime":0,"mStepCount":0,"mTimeUnit":600000,"mTotalActiveTime":0.0,"mWalkStepCount":0},{"mCalorie":9.52999997138977,"mDistance":178.94000339508057,"mNowHealthyStep":0,"mRunStepCount":0,"mSpeed":4.901883125305176,"mStartTime":0,"mStepCount":236,"mTimeUnit":600000,"mTotalActiveTime":131415.6203659542,"mWalkStepCount":236},{"mCalorie":0.0,"mDistance":0.0,"mNowHealthyStep":0,"mRunStepCount":0,"mSpeed":0.0,"mStartTime":0,"mStepCount":0,"mTimeUnit":600000,"mTotalActiveTime":0.0,"mWalkStepCount":0},{"mCalorie":0.0,"mDistance":0.0,"mNowHealthyStep":0,"mRunStepCount":0,"mSpeed":0.0,"mStartTime":0,"mStepCount":0,"mTimeUnit":600000,"mTotalActiveTime":0.0,"mWalkStepCount":0},{"mCalorie":0.0,"mDistance":0.0,"mNowHealthyStep":0,"mRunStepCount":0,"mSpeed":0.0,"mStartTime":0,"mStepCount":0,"mTimeUnit":600000,"mTotalActiveTime":0.0,"mWalkStepCount":0},{"mCalorie":0.8399999737739563,"mDistance":14.84000015258789,"mNowHealthyStep":0,"mRunStepCount":0,"mSpeed":4.400000095367432,"mStartTime":0,"mStepCount":20,"mTimeUnit":600000,"mTotalActiveTime":12141.818043496,"mWalkStepCount":20},{"mCalorie":0.0,"mDistance":0.0,"mNowHealthyStep":0,"mRunStepCount":0,"mSpeed":0.0,"mStartTime":0,"mStepCount":0,"mTimeUnit":600000,"mTotalActiveTime":0.0,"mWalkStepCount":0},{"mCalorie":0.0,"mDistance":0.0,"mNowHealthyStep":0,"mRunStepCount":0,"mSpeed":0.0,"mStartTime":0,"mStepCount":0,"mTimeUnit":600000,"mTotalActiveTime":0.0,"mWalkStepCount":0},{"mCalorie":0.0,"mDistance":0.0,"mNowHealthyStep":0,"mRunStepCount":0,"mSpeed":0.0,"mStartTime":0,"mStepCount":0,"mTimeUnit":600000,"mTotalActiveTime":0.0,"mWalkStepCount":0},{"mCalorie":0.0,"mDistance":0.0,"mNowHealthyStep":0,"mRunStepCount":0,"mSpeed":0.0,"mStartTime":0,"mStepCount":0,"mTimeUnit":600000,"mTotalActiveTime":0.0,"mWalkStepCount":0},{"mCalorie":0.0,"mDistance":0.0,"mNowHealthyStep":0,"mRunStepCount":0,"mSpeed":0.0,"mStartTime":0,"mStepCount":0,"mTimeUnit":600000,"mTotalActiveTime":0.0,"mWalkStepCount":0},{"mCalorie":0.0,"mDistance":0.0,"mNowHealthyStep":0,"mRunStepCount":0,"mSpeed":0.0,"mStartTime":0,"mStepCount":0,"mTimeUnit":600000,"mTotalActiveTime":0.0,"mWalkStepCount":0},{"mCalorie":0.0,"mDistance":0.0,"mNowHealthyStep":0,"mRunStepCount":0,"mSpeed":0.0,"mStartTime":0,"mStepCount":0,"mTimeUnit":600000,"mTotalActiveTime":0.0,"mWalkStepCount":0},{"mCalorie":3.8499999791383743,"mDistance":73.58999919891357,"mNowHealthyStep":0,"mRunStepCount":0,"mSpeed":5.4145050048828125,"mStartTime":0,"mStepCount":95,"mTimeUnit":600000,"mTotalActiveTime":48928.57029256575,"mWalkStepCount":95},{"mCalorie":0.0,"mDistance":0.0,"mNowHealthyStep":0,"mRunStepCount":0,"mSpeed":0.0,"mStartTime":0,"mStepCount":0,"mTimeUnit":600000,"mTotalActiveTime":0.0,"mWalkStepCount":0},{"mCalorie":9.889999836683273,"mDistance":184.0299940109253,"mNowHealthyStep":0,"mRunStepCount":0,"mSpeed":4.617196083068848,"mStartTime":0,"mStepCount":245,"mTimeUnit":600000,"mTotalActiveTime":143487.08086378418,"mWalkStepCount":245},{"mCalorie":0.0,"mDistance":0.0,"mNowHealthyStep":0,"mRunStepCount":0,"mSpeed":0.0,"mStartTime":0,"mStepCount":0,"mTimeUnit":600000,"mTotalActiveTime":0.0,"mWalkStepCount":0},{"mCalorie":6.540000081062317,"mDistance":117.19000053405762,"mNowHealthyStep":0,"mRunStepCount":0,"mSpeed":4.3486833572387695,"mStartTime":0,"mStepCount":161,"mTimeUnit":600000,"mTotalActiveTime":97014.1867321232,"mWalkStepCount":161},{"mCalorie":0.0,"mDistance":0.0,"mNowHealthyStep":0,"mRunStepCount":0,"mSpeed":0.0,"mStartTime":0,"mStepCount":0,"mTimeUnit":600000,"mTotalActiveTime":0.0,"mWalkStepCount":0},{"mCalorie":0.6200000643730164,"mDistance":13.289999008178711,"mNowHealthyStep":0,"mRunStepCount":0,"mSpeed":5.781927108764648,"mStartTime":0,"mStepCount":17,"mTimeUnit":600000,"mTotalActiveTime":8274.749150143747,"mWalkStepCount":17},{"mCalorie":0.0,"mDistance":0.0,"mNowHealthyStep":0,"mRunStepCount":0,"mSpeed":0.0,"mStartTime":0,"mStepCount":0,"mTimeUnit":600000,"mTotalActiveTime":0.0,"mWalkStepCount":0},{"mCalorie":0.0,"mDistance":0.0,"mNowHealthyStep":0,"mRunStepCount":0,"mSpeed":0.0,"mStartTime":0,"mStepCount":0,"mTimeUnit":600000,"mTotalActiveTime":0.0,"mWalkStepCount":0},{"mCalorie":0.0,"mDistance":0.0,"mNowHealthyStep":0,"mRunStepCount":0,"mSpeed":0.0,"mStartTime":0,"mStepCount":0,"mTimeUnit":600000,"mTotalActiveTime":0.0,"mWalkStepCount":0},{"mCalorie":0.0,"mDistance":0.0,"mNowHealthyStep":0,"mRunStepCount":0,"mSpeed":0.0,"mStartTime":0,"mStepCount":0,"mTimeUnit":600000,"mTotalActiveTime":0.0,"mWalkStepCount":0},{"mCalorie":0.0,"mDistance":0.0,"mNowHealthyStep":0,"mRunStepCount":0,"mSpeed":0.0,"mStartTime":0,"mStepCount":0,"mTimeUnit":600000,"mTotalActiveTime":0.0,"mWalkStepCount":0},{"mCalorie":0.0,"mDistance":0.0,"mNowHealthyStep":0,"mRunStepCount":0,"mSpeed":0.0,"mStartTime":0,"mStepCount":0,"mTimeUnit":600000,"mTotalActiveTime":0.0,"mWalkStepCount":0},{"mCalorie":0.0,"mDistance":0.0,"mNowHealthyStep":0,"mRunStepCount":0,"mSpeed":0.0,"mStartTime":0,"mStepCount":0,"mTimeUnit":600000,"mTotalActiveTime":0.0,"mWalkStepCount":0},{"mCalorie":0.0,"mDistance":0.0,"mNowHealthyStep":0,"mRunStepCount":0,"mSpeed":0.0,"mStartTime":0,"mStepCount":0,"mTimeUnit":600000,"mTotalActiveTime":0.0,"mWalkStepCount":0},{"mCalorie":0.0,"mDistance":0.0,"mNowHealthyStep":0,"mRunStepCount":0,"mSpeed":0.0,"mStartTime":0,"mStepCount":0,"mTimeUnit":600000,"mTotalActiveTime":0.0,"mWalkStepCount":0}]