{"mAdaptiveGoal":0,"mIsGoalAchieved":false,"mIsMostActiveAchieved":false,"mMostActiveMinutes":225,"mStreakDayCount":0,"mUnitDataList":[{"distance":11.17,"mCalorie":0.64,"mOthersTime":0,"mRunTime":0,"mStartTime":37800000,"mTimeUnit":600000,"mWalkTime":10005,"runStep":0,"walkStep":15},{"distance":4.58,"mCalorie":0.25,"mOthersTime":0,"mRunTime":0,"mStartTime":39600000,"mTimeUnit":600000,"mWalkTime":4002,"runStep":0,"walkStep":6},{"distance":16.849998,"mCalorie":0.99,"mOthersTime":0,"mRunTime":0,"mStartTime":40200000,"mTimeUnit":600000,"mWalkTime":15341,"runStep":0,"walkStep":23},{"distance":32.12,"mCalorie":1.88,"mOthersTime":0,"mRunTime":0,"mStartTime":40800000,"mTimeUnit":600000,"mWalkTime":29348,"runStep":0,"walkStep":44},{"distance":46.93,"mCalorie":2.68,"mOthersTime":0,"mRunTime":0,"mStartTime":41400000,"mTimeUnit":600000,"mWalkTime":42021,"runStep":0,"walkStep":63},{"distance":17.33,"mCalorie":0.95,"mOthersTime":0,"mRunTime":0,"mStartTime":49200000,"mTimeUnit":600000,"mWalkTime":15341,"runStep":0,"walkStep":23},{"distance":45.72,"mCalorie":2.6,"mOthersTime":0,"mRunTime":0,"mStartTime":49800000,"mTimeUnit":600000,"mWalkTime":41354,"runStep":0,"walkStep":62},{"distance":31.57,"mCalorie":1.73,"mOthersTime":0,"mRunTime":0,"mStartTime":50400000,"mTimeUnit":600000,"mWalkTime":28014,"runStep":0,"walkStep":42},{"distance":16.18,"mCalorie":0.9199999,"mOthersTime":0,"mRunTime":0,"mStartTime":51600000,"mTimeUnit":600000,"mWalkTime":14674,"runStep":0,"walkStep":22},{"distance":43.18,"mCalorie":2.42,"mOthersTime":0,"mRunTime":0,"mStartTime":57000000,"mTimeUnit":600000,"mWalkTime":39353,"runStep":0,"walkStep":59},{"distance":6.71,"mCalorie":0.38,"mOthersTime":0,"mRunTime":0,"mStartTime":61200000,"mTimeUnit":600000,"mWalkTime":6003,"runStep":0,"walkStep":9},{"distance":16.0,"mCalorie":0.91,"mOthersTime":0,"mRunTime":0,"mStartTime":61800000,"mTimeUnit":600000,"mWalkTime":14674,"runStep":0,"walkStep":22},{"distance":23.349998,"mCalorie":1.3299999,"mOthersTime":0,"mRunTime":0,"mStartTime":64200000,"mTimeUnit":600000,"mWalkTime":21344,"runStep":0,"walkStep":32},{"distance":14.0,"mCalorie":0.81,"mOthersTime":0,"mRunTime":0,"mStartTime":66600000,"mTimeUnit":600000,"mWalkTime":12673,"runStep":0,"walkStep":19},{"distance":10.09,"mCalorie":0.53,"mOthersTime":0,"mRunTime":0,"mStartTime":75000000,"mTimeUnit":600000,"mWalkTime":8671,"runStep":0,"walkStep":13},{"distance":11.2,"mCalorie":0.62,"mOthersTime":0,"mRunTime":0,"mStartTime":78000000,"mTimeUnit":600000,"mWalkTime":10005,"runStep":0,"walkStep":15},{"distance":53.47,"mCalorie":3.0600002,"mOthersTime":0,"mRunTime":0,"mStartTime":81000000,"mTimeUnit":600000,"mWalkTime":48691,"runStep":0,"walkStep":73},{"distance":23.039995,"mCalorie":1.2300001,"mOthersTime":0,"mRunTime":0,"mStartTime":85200000,"mTimeUnit":600000,"mWalkTime":20677,"runStep":0,"walkStep":31}],"version":1}